cdk_cloudformation_gitlab_groups_groupaccesstogroup/__init__.py
cdk_cloudformation_gitlab_groups_groupaccesstogroup/py.typed
cdk_cloudformation_gitlab_groups_groupaccesstogroup/_jsii/__init__.py
cdk_cloudformation_gitlab_groups_groupaccesstogroup/_jsii/gitlab-groups-groupaccesstogroup@1.2.0-alpha.7.jsii.tgz
cdk_cloudformation_gitlab_groups_groupaccesstogroup-1.2.0a7.dist-info/LICENSE
cdk_cloudformation_gitlab_groups_groupaccesstogroup-1.2.0a7.dist-info/METADATA
cdk_cloudformation_gitlab_groups_groupaccesstogroup-1.2.0a7.dist-info/WHEEL
cdk_cloudformation_gitlab_groups_groupaccesstogroup-1.2.0a7.dist-info/top_level.txt
cdk_cloudformation_gitlab_groups_groupaccesstogroup-1.2.0a7.dist-info/RECORD
